beeperpurge/__init__.py
beeperpurge/__version__.py
beeperpurge/cleaner.py
beeperpurge/logging.py
beeperpurge-1.0.19.dist-info/LICENSE
beeperpurge-1.0.19.dist-info/METADATA
beeperpurge-1.0.19.dist-info/WHEEL
beeperpurge-1.0.19.dist-info/entry_points.txt
beeperpurge-1.0.19.dist-info/top_level.txt
beeperpurge-1.0.19.dist-info/RECORD
