Metadata-Version: 2.1
Name: beeperpurge
Version: 1.0.19
Summary: High-throughput parallel file system cleaner
Author-email: Alon Almog <alon.almog@rivery.io>
License: MIT
Requires-Python: >=3.9
License-File: LICENSE
Provides-Extra: dev
Requires-Dist: pytest>=7.0; extra == "dev"
Requires-Dist: pytest-cov; extra == "dev"
Requires-Dist: pytest-mock; extra == "dev"
